solution_efe_function/__init__.py
solution_efe_function/functions.py
solution_efe_function-1.0.0.dist-info/METADATA
solution_efe_function-1.0.0.dist-info/WHEEL
solution_efe_function-1.0.0.dist-info/top_level.txt
solution_efe_function-1.0.0.dist-info/RECORD
