Metadata-Version: 2.1
Name: solution-efe-function
Version: 1.0.0
Summary: Paquete de funciones
Home-page: UNKNOWN
Author: Rulman Ferro
Author-email: rulman26@gmail.com
License: MIT
Platform: UNKNOWN
Requires-Python: >=3.6
